yellowbox_snowglobe/__init__.py
yellowbox_snowglobe/_version.py
yellowbox_snowglobe/api.py
yellowbox_snowglobe/case_mode.py
yellowbox_snowglobe/schema_init.py
yellowbox_snowglobe/service.py
yellowbox_snowglobe/session.py
yellowbox_snowglobe/snow_to_post.py
yellowbox_snowglobe-0.2.6.dist-info/LICENSE
yellowbox_snowglobe-0.2.6.dist-info/METADATA
yellowbox_snowglobe-0.2.6.dist-info/WHEEL
yellowbox_snowglobe-0.2.6.dist-info/RECORD
